in_container/__init__.py
in_container/in_container.py
tests/__init__.py
tests/test_in_container.py
in_container-0.7.dist-info/LICENSE
in_container-0.7.dist-info/METADATA
in_container-0.7.dist-info/WHEEL
in_container-0.7.dist-info/top_level.txt
in_container-0.7.dist-info/RECORD
